setup.py
pytrade/EconItem.py
pytrade/EconTradeOffer.py
pytrade/__init__.py
pytrade/confirmations.py
pytrade/login.py
pytrade/manager_trade.py
pytrade/steam_enums.py
steam_trade.egg-info/PKG-INFO
steam_trade.egg-info/SOURCES.txt
steam_trade.egg-info/dependency_links.txt
steam_trade.egg-info/requires.txt
steam_trade.egg-info/top_level.txt