Metadata-Version: 1.0
Name: steam-trade
Version: 2.1.0
Summary: An Asynchronous, event based steam trade library
Home-page: https://github.com/Zwork101/steam-trade
Author: Zwork101
Author-email: zwork101@gmail.com
License: MIT
Platform: UNKNOWN
